Proyecto/src/design/7segpersonal.sv
module sevenseg_display_single (
    input  logic [3:0] numero_binario,  // número 0-15 a mostrar
    output logic [6:0] seg_o,           // segmentos a-g
    output logic an_o                    // control de transistor / pin FPGA
);

    wire A, B, C, D;

    // Mapear bits del número a variables para claridad
    assign A = numero_binario[3];
    assign B = numero_binario[2];
    assign C = numero_binario[1];
    assign D = numero_binario[0];

    // Lógica para cada segmento (a-g)
    assign seg_o[0] = (~A & B & D) |               // segmento A
                    (~A & C) |
                    (A & ~B & ~C) |
                    (A & ~D) |
                    (~B & ~D) |
                    (B & C);  

assign seg_o[1] = (~B & ~D) |     // segmento B
                    (~B  & ~C) |
                    (~A & ~C & ~D) |
                    (A & ~C & D) |
                    (~A & C & D); 

assign seg_o[2] = (~B & ~C) |     // segmento C
                    (~C & D) |
                    (~A & B) |
                    (A & ~B) |
                    (~B & D);        

assign seg_o[3] = (~B & ~C & ~D) |     // segmento D
                    (A & B & ~D) |
                    (B & ~C & D) |
                    (~B & C & D) |
                    (~A & C & ~D);

assign seg_o[4] = (~B & ~D) |          // segmento E
                    (A & B) |
                    (A & C) |
                    (C & ~D);

assign seg_o[5] = (~C & ~D) |         // segmento F
                    (~A & B & ~C) |
                    (A & ~B ) |
                    (B & ~D) |
                    (A & C); 

assign seg_o[6] = (~B & C) |         // segmento G
                    (C & ~D) |
                    (A & ~B) |
                    (A & D)|
                    (~A & B & ~C);       

                  
    
    // Siempre habilitado para un solo display
    assign an_o = 1'b1;

endmodule

Proyecto/src/design/error_gen.sv
module error_gen (
    input  logic [6:0] hamming_in,
    input  logic [2:0] idx, /*Idx hay que cambiarlo por el sw o como sea que se llame las entradas que indican donde poner el erorr idx=0 no error, idx=1 error en bit 0, idx=2 error en bit 1, ..., idx=6 error en bit 6 */
    output logic [3:0] i,
    output logic [2:0] c
);

    logic [6:0] resultado_con_error;

    // Flip selected bit
    assign resultado_con_error = (idx == 3'd0) ? 
                             hamming_in :
                             (hamming_in ^ (7'b1 << (idx - 1)));

    //Extraccion y entrega segun formato solicitado
    assign i[3] = resultado_con_error[6];
    assign i[2] = resultado_con_error[5];
    assign i[1] = resultado_con_error[4];
    assign i[0] = resultado_con_error[2];

    assign c[2] = resultado_con_error[3];
    assign c[1] = resultado_con_error[1];
    assign c[0] = resultado_con_error[0];

endmodule

Proyecto/src/design/module_hamming.sv

module module_hamming (


    input logic [3:0] Numero_binario,

    output logic [6:0] hamming
 
);

logic P1, P2, P3;
logic D1, D2, D3, D4;

assign D1 = Numero_binario[0];
assign D2 = Numero_binario[1];
assign D3 = Numero_binario[2];
assign D4 = Numero_binario[3];

assign P1 = D1^D2^D4;
assign P2 = D1^D3^D4;
assign P3 = D2^D3^D4;

assign hamming[0]=P1;
assign hamming[1]=P2;
assign hamming[2]=D1;
assign hamming[3]=P3;
assign hamming[4]=D2;
assign hamming[5]=D3;
assign hamming[6]=D4;
 
 



endmodule

Proyecto/src/design/top_hamming.sv
module top_hamming ( /*Las entradas y salidas que se instancian el parentesis son las que interactuan con el mundo exterior, sea que entren de el o salgan a el mundo exterior, como los switches, leds, displays, etc. */

    input  logic [3:0] Numero_binario,
    input  logic [2:0] idx,

    output logic [6:0] seg_o,
    output logic an_o,
    output logic [3:0] i,
    output logic [2:0] c
);
    // Señales internas
    logic [6:0] hamming_out;
    

    // Instancia: Generador Hamming
 
    module_hamming u_hamming (
        .Numero_binario(Numero_binario),
        .hamming(hamming_out)
    );

    // Instancia: Generador de error
    error_gen u_error (
    .hamming_in(hamming_out),
    .idx(idx),
    .i(i),
    .c(c)
);
    // Instancia: Display 7 segmentos
    sevenseg_display_single u_display (
        .numero_binario(i),
        .seg_o(seg_o),
        .an_o(an_o)
    );

endmodule

Proyecto/src/sim/top_tb.sv
`timescale 1ns/1ps

module tb_top_hamming;

    // Señales de prueba
    logic [3:0] Numero_binario;
    logic [2:0] idx;
    logic [3:0] i;
    logic [2:0] c;
    logic [6:0] seg_o;
    logic an_o;

    // Instancia del DUT (Device Under Test)
    top_hamming dut (
        .Numero_binario(Numero_binario),
        .idx(idx),
        .seg_o(seg_o),
        .an_o(an_o),
        .i(i),
        .c(c)
    );
    initial begin
        $dumpfile("top_hamming_tb.vcd"); 
        $dumpvars(0, tb_top_hamming);
    end
    // Proceso de estímulos
    initial begin
        // Inicialización
        Numero_binario = 4'b0000;
        idx = 3'd0;

        // Espera inicial
        #10;
        $display("t=%0t | Num=%b | idx=%d | i=%b | c=%b", $time, Numero_binario, idx, i, c);
        // =========================
        // Prueba sin error
        // =========================
        Numero_binario = 4'b0101; // 5
        idx = 3'd0;               // sin error
        #20;
        $display("t=%0t | Num=%b | idx=%d | i=%b | c=%b", $time, Numero_binario, idx, i, c);

        // =========================
        // Prueba con errores en distintos bits
        // =========================
        idx = 3'd1; // error en bit 0
        #20;
        $display("t=%0t | Num=%b | idx=%d | i=%b | c=%b", $time, Numero_binario, idx, i, c);


        idx = 3'd2; // error en bit 1
        #20;
        $display("t=%0t | Num=%b | idx=%d | i=%b | c=%b", $time, Numero_binario, idx, i, c);


        idx = 3'd3; // error en bit 2
        #20;
        $display("t=%0t | Num=%b | idx=%d | i=%b | c=%b", $time, Numero_binario, idx, i, c);


        idx = 3'd4; // error en bit 3
        #20;
        $display("t=%0t | Num=%b | idx=%d | i=%b | c=%b", $time, Numero_binario, idx, i, c);


        idx = 3'd5; // error en bit 4
        #20;
        $display("t=%0t | Num=%b | idx=%d | i=%b | c=%b", $time, Numero_binario, idx, i, c);


        idx = 3'd6; // error en bit 5
        #20;
        $display("t=%0t | Num=%b | idx=%d | i=%b | c=%b", $time, Numero_binario, idx, i, c);


        idx = 3'd7; // error en bit 6
        #20;
        $display("t=%0t | Num=%b | idx=%d | i=%b | c=%b", $time, Numero_binario, idx, i, c);


        // =========================
        // Cambiar dato de entrada
        // =========================
        Numero_binario = 4'b1010; // 10
        idx = 3'd0;
        #20;
        $display("t=%0t | Num=%b | idx=%d | i=%b | c=%b", $time, Numero_binario, idx, i, c);


        idx = 3'd3;
        #20;
        $display("t=%0t | Num=%b | idx=%d | i=%b | c=%b", $time, Numero_binario, idx, i, c);
        
        // =========================
        // Finalizar simulación
        // =========================
        $finish;
    end

endmodule

Proyecto/src/build/top_hamming_tb.vcd
$date
	Fri Apr 10 14:16:09 2026
$end
$version
	Icarus Verilog
$end
$timescale
	1ps
$end
$scope module tb_top_hamming $end
$var wire 1 ! an_o $end
$var wire 7 " seg_o [6:0] $end
$var wire 4 # i [3:0] $end
$var wire 3 $ c [2:0] $end
$var reg 4 % Numero_binario [3:0] $end
$var reg 3 & idx [2:0] $end
$scope module dut $end
$var wire 4 ' Numero_binario [3:0] $end
$var wire 1 ! an_o $end
$var wire 3 ( idx [2:0] $end
$var wire 7 ) seg_o [6:0] $end
$var wire 4 * i [3:0] $end
$var wire 7 + hamming_out [6:0] $end
$var wire 3 , c [2:0] $end
$scope module u_display $end
$var wire 1 ! an_o $end
$var wire 7 - seg_o [6:0] $end
$var wire 4 . numero_binario [3:0] $end
$var wire 1 / D $end
$var wire 1 0 C $end
$var wire 1 1 B $end
$var wire 1 2 A $end
$upscope $end
$scope module u_error $end
$var wire 3 3 idx [2:0] $end
$var wire 7 4 resultado_con_error [6:0] $end
$var wire 4 5 i [3:0] $end
$var wire 7 6 hamming_in [6:0] $end
$var wire 3 7 c [2:0] $end
$upscope $end
$scope module u_hamming $end
$var wire 4 8 Numero_binario [3:0] $end
$var wire 1 9 P1 $end
$var wire 1 : P2 $end
$var wire 1 ; P3 $end
$var wire 7 < hamming [6:0] $end
$var wire 1 = D4 $end
$var wire 1 > D3 $end
$var wire 1 ? D2 $end
$var wire 1 @ D1 $end
$upscope $end
$upscope $end
$upscope $end
$enddefinitions $end
$comment Show the parameter values. $end
$dumpall
$end
#0
$dumpvars
0@
0?
0>
0=
b0 <
0;
0:
09
b0 8
b0 7
b0 6
b0 5
b0 4
b0 3
02
01
00
0/
b0 .
b111111 -
b0 ,
b0 +
b0 *
b111111 )
b0 (
b0 '
b0 &
b0 %
b0 $
b0 #
b111111 "
1!
$end
#10000
b1101101 "
b1101101 )
b1101101 -
b101 $
b101 ,
b101 7
11
1/
19
b101 #
b101 *
b101 .
b101 5
1;
b101101 4
1@
b101101 +
b101101 6
b101101 <
1>
b101 %
b101 '
b101 8
#30000
b100 $
b100 ,
b100 7
b101100 4
b1 &
b1 (
b1 3
#50000
b111 $
b111 ,
b111 7
b101111 4
b10 &
b10 (
b10 3
#70000
b1100110 "
b1100110 )
b1100110 -
0/
b100 #
b100 *
b100 .
b100 5
b101 $
b101 ,
b101 7
b101001 4
b11 &
b11 (
b11 3
#90000
b1101101 "
b1101101 )
b1101101 -
1/
b101 #
b101 *
b101 .
b101 5
b1 $
b1 ,
b1 7
b100101 4
b100 &
b100 (
b100 3
#110000
b111 "
b111 )
b111 -
10
b111 #
b111 *
b111 .
b111 5
b101 $
b101 ,
b101 7
b111101 4
b101 &
b101 (
b101 3
#130000
b110 "
b110 )
b110 -
01
00
b1 #
b1 *
b1 .
b1 5
b1101 4
b110 &
b110 (
b110 3
#150000
b1011110 "
b1011110 )
b1011110 -
12
11
b1101 #
b1101 *
b1101 .
b1101 5
b1101101 4
b111 &
b111 (
b111 3
#170000
b1110111 "
b1110111 )
b1110111 -
b10 $
b10 ,
b10 7
01
10
0/
b1010 #
b1010 *
b1010 .
b1010 5
0;
1:
09
b1010010 4
0@
1?
0>
b1010010 +
b1010010 6
b1010010 <
1=
b0 &
b0 (
b0 3
b1010 %
b1010 '
b1010 8
#190000
b1111100 "
b1111100 )
b1111100 -
1/
b1011 #
b1011 *
b1011 .
b1011 5
b1010110 4
b11 &
b11 (
b11 3
